MANIFEST.in
README.md
setup.cfg
setup.py
bin/dyson
bin/dyson-suite
bin/dyson-test
docs/actions.md
docs/alerts.md
docs/applications.md
docs/cli.md
docs/configuration.md
docs/cookies.md
docs/creating_modules.md
docs/getting_started.md
docs/keywords.md
docs/modules.md
docs/selectors.md
docs/storing_variables.md
docs/todo.md
docs/validations.md
docs/variables.md
docs/waiting.md
docs/windows.md
dyson.egg-info/PKG-INFO
dyson.egg-info/SOURCES.txt
dyson.egg-info/dependency_links.txt
dyson.egg-info/requires.txt
dyson.egg-info/top_level.txt
lib/dyson/__init__.py
lib/dyson/__init__.pyc
lib/dyson/constants.py
lib/dyson/__pycache__/__init__.cpython-35.pyc
lib/dyson/__pycache__/constants.cpython-35.pyc
lib/dyson/cli/__init__.py
lib/dyson/cli/__init__.pyc
lib/dyson/cli/adhoc.py
lib/dyson/cli/adhoc.pyc
lib/dyson/cli/suite.py
lib/dyson/cli/test.py
lib/dyson/cli/test.pyc
lib/dyson/cli/__pycache__/__init__.cpython-35.pyc
lib/dyson/cli/__pycache__/adhoc.cpython-35.pyc
lib/dyson/cli/__pycache__/suite.cpython-35.pyc
lib/dyson/cli/__pycache__/test.cpython-35.pyc
lib/dyson/errors/__init__.py
lib/dyson/errors/__pycache__/__init__.cpython-35.pyc
lib/dyson/keywords/__init__.py
lib/dyson/keywords/__pycache__/__init__.cpython-35.pyc
lib/dyson/modules/__init__.py
lib/dyson/modules/__pycache__/__init__.cpython-35.pyc
lib/dyson/modules/core/__init__.py
lib/dyson/modules/core/__pycache__/__init__.cpython-35.pyc
lib/dyson/modules/core/actions/__init__.py
lib/dyson/modules/core/actions/check.py
lib/dyson/modules/core/actions/click.py
lib/dyson/modules/core/actions/get_attribute.py
lib/dyson/modules/core/actions/get_text.py
lib/dyson/modules/core/actions/set_text.py
lib/dyson/modules/core/actions/switch_to.py
lib/dyson/modules/core/actions/uncheck.py
lib/dyson/modules/core/actions/__pycache__/__init__.cpython-35.pyc
lib/dyson/modules/core/actions/__pycache__/check.cpython-35.pyc
lib/dyson/modules/core/actions/__pycache__/click.cpython-35.pyc
lib/dyson/modules/core/actions/__pycache__/get_attribute.cpython-35.pyc
lib/dyson/modules/core/actions/__pycache__/get_text.cpython-35.pyc
