Metadata-Version: 1.1
Name: dyson
Version: 1.1.2
Summary: Dyson Selenium framework.
Home-page: https://github.com/dynamictivity/dyson
Author: Dan Davison
Author-email: sircapsalot@gmail.com
License: Apache 2
Download-URL: https://github.com/dynamictivity/dyson/tarball/1.1.2
Keywords: selenium,testing
Platform: UNKNOWN
